GNUmakefile
INSTALL.txt
LICENSE.txt
MANIFEST
PKG-INFO
README.txt
aspects.py
setup.py
examples/httpget_example.py
examples/timeout_advice.py
examples/timeout_example.py
examples/tracer_advice.py
examples/tracer_example.py
examples/typecheck_advice.py
examples/typecheck_example.py
python_aspects.egg-info/PKG-INFO
python_aspects.egg-info/SOURCES.txt
python_aspects.egg-info/dependency_links.txt
python_aspects.egg-info/top_level.txt
test/test_aspects.py
test/test_with_wrap.py
test/testlib_with_wrap.py