Metadata-Version: 1.0
Name: python-aspects
Version: 1.1
Summary: Lightweight AOP extension
Home-page: http://www.cs.tut.fi/~ask/aspects/index.html
Author: Antti Kervinen
Author-email: ask@cs.tut.fi
License: UNKNOWN
Platform: UNKNOWN
